{
  "trigger": true,
  "modules": [
    "add-to-group"
  ],
  "parentResource": "AWSCrud",
  "functionName": "AWSCrudPostConfirmation",
  "resourceName": "AWSCrudPostConfirmation",
  "parentStack": "auth",
  "triggerEnvs": [],
  "triggerDir": "C:\\Users\\manju\\AppData\\Roaming\\npm\\node_modules\\@aws-amplify\\cli\\node_modules\\amplify-category-auth\\provider-utils\\awscloudformation\\triggers\\PostConfirmation",
  "triggerTemplate": "PostConfirmation.json.ejs",
  "roleName": "AWSCrudPostConfirmation",
  "skipEdit": true,
  "GROUP": "CrudUsers"
}